starlette_dishka/__init__.py
starlette_dishka/container.py
starlette_dishka/integration.py
starlette_dishka/provider.py
starlette_dishka/py.typed
starlette_dishka-1.0.1.dist-info/WHEEL
starlette_dishka-1.0.1.dist-info/METADATA
starlette_dishka-1.0.1.dist-info/RECORD
