Metadata-Version: 2.3
Name: starlette-dishka
Version: 1.0.1
Summary: Starlette integration for dishka
Author: Andrey Tikhonov
Author-email: Andrey Tikhonov <17@itishka.org>
License: Apache-2.0
Classifier: Programming Language :: Python
Classifier: Programming Language :: Python :: 3
Classifier: Programming Language :: Python :: 3.10
Classifier: Programming Language :: Python :: 3.11
Classifier: Programming Language :: Python :: 3.12
Classifier: Programming Language :: Python :: 3.13
Classifier: Programming Language :: Python :: 3.14
Classifier: Topic :: Software Development :: Libraries
Classifier: Typing :: Typed
Classifier: Intended Audience :: Developers
Classifier: License :: OSI Approved :: Apache Software License
Classifier: Operating System :: OS Independent
Classifier: Development Status :: 5 - Production/Stable
Requires-Dist: dishka>=1.7.1,<2.0.0
Requires-Dist: starlette>=0.27.0
Requires-Python: >=3.10
Project-URL: Bug Tracker, https://github.com/reagento/starlette-dishka
Project-URL: Download, https://github.com/reagento/starlette-dishka/#files
Project-URL: Homepage, https://github.com/reagento/starlette-dishka
Project-URL: Source, https://github.com/reagento/starlette-dishka
